{
  "tags": {
    "allowUnknownTags": true,
    "dictionaries": ["jsdoc"]
  },
  "plugins": [
    "plugins/markdown",
    "node_modules/better-docs/typescript",
    "node_modules/better-docs/category"
  ],
  "source": {
    "include": ["src", "README.md"],
    "includePattern": "\\.(jsx|js|ts|tsx)$",
    "excludePattern": "(node_modules/|docs)"
  },
  "templates": {
    "cleverLinks": false,
    "monospaceLinks": true,
    "useLongnameInNav": false,
    "showInheritedInNav": true,
    "better-docs": {
      "name": "Ravenite (ravencoin-rpc)",
      "title": "Ravenite - Ravencoin RPC",
      "hideGenerator": true,
      "navLinks": [
        {
          "label": "Github",
          "href": "https://github.com/Ravenites/ravencoin-rpc"
        }
      ]
    }
  },
  "opts": {
    "destination": "./docs/",
    "encoding": "utf8",
    "readme": "README.md",
    "recurse": true,
    "verbose": true,
    "template": "node_modules/better-docs"
  }
}
